AUTHORS
LICENSE
MANIFEST.in
README.md
pyproject.toml
src/opentaskpy/addons/gcp/__init__.py
src/opentaskpy/addons/gcp/remotehandlers/__init__.py
src/opentaskpy/addons/gcp/remotehandlers/bucket.py
src/opentaskpy/addons/gcp/remotehandlers/creds.py
src/opentaskpy/addons/gcp/remotehandlers/schemas/transfer/bucket_destination.json
src/opentaskpy/addons/gcp/remotehandlers/schemas/transfer/bucket_source.json
src/opentaskpy/addons/gcp/remotehandlers/schemas/transfer/bucket_destination/protocol.json
src/opentaskpy/addons/gcp/remotehandlers/schemas/transfer/bucket_destination/rename.json
src/opentaskpy/addons/gcp/remotehandlers/schemas/transfer/bucket_source/fileWatch.json
src/opentaskpy/addons/gcp/remotehandlers/schemas/transfer/bucket_source/postCopyAction.json
src/opentaskpy/addons/gcp/remotehandlers/schemas/transfer/bucket_source/protocol.json
src/otf_addons_gcp.egg-info/PKG-INFO
src/otf_addons_gcp.egg-info/SOURCES.txt
src/otf_addons_gcp.egg-info/dependency_links.txt
src/otf_addons_gcp.egg-info/requires.txt
src/otf_addons_gcp.egg-info/top_level.txt
tests/test_download.py
tests/test_local_to_root.py
tests/test_schema.py
tests/test_upload_nested.py