Metadata-Version: 2.1
Name: otf-addons-gcp
Version: 24.32.0
Summary: Addons for opentaskpy, giving it the ability to push/pull files via GCP Cloud Storage.
Author-email: Aldo Troiano <a.troiano@reply.com>
License: GPLv3
Project-URL: Homepage, https://github.com/adammcdonagh/otf-addons-gcp
Project-URL: Bug Tracker, https://github.com/adammcdonagh/otf-addons-gcp/issues
Project-URL: Changelog, https://github.com/adammcdonagh/otf-addons-gcp/blob/main/CHANGELOG.md
Keywords: automation,task,framework,gcp,cloudstorage,otf
Classifier: Programming Language :: Python :: 3
Classifier: License :: OSI Approved :: GNU General Public License v3 (GPLv3)
Classifier: Operating System :: POSIX
Requires-Python: >=3.11
License-File: LICENSE
License-File: AUTHORS
Requires-Dist: google-auth>=v2.3.0
Requires-Dist: opentaskpy>=v24.23.0
Provides-Extra: dev
Requires-Dist: localstack; extra == "dev"
Requires-Dist: localstack-client; extra == "dev"
Requires-Dist: pytest-shell; extra == "dev"
Requires-Dist: types-requests; extra == "dev"
Requires-Dist: types-python-dateutil; extra == "dev"
Requires-Dist: black>=24.1.1; extra == "dev"
Requires-Dist: isort; extra == "dev"
Requires-Dist: pytest; extra == "dev"
Requires-Dist: bumpver; extra == "dev"
Requires-Dist: pytest-shell; extra == "dev"
Requires-Dist: lovely-pytest-docker; extra == "dev"
Requires-Dist: pre-commit; extra == "dev"
Requires-Dist: pylint; extra == "dev"
Requires-Dist: pydantic; extra == "dev"
Requires-Dist: mypy; extra == "dev"
Requires-Dist: ruff; extra == "dev"
Requires-Dist: coverage; extra == "dev"
Requires-Dist: pytest-cov; extra == "dev"
Requires-Dist: moto[ecs]; extra == "dev"
Requires-Dist: freezegun; extra == "dev"
